BACAP_Parser/AdvType.py
BACAP_Parser/Advancement.py
BACAP_Parser/Color.py
BACAP_Parser/Criteria.py
BACAP_Parser/CriteriaList.py
BACAP_Parser/Datapack.py
BACAP_Parser/ExtendedDict.py
BACAP_Parser/Item.py
BACAP_Parser/PackMCMeta.py
BACAP_Parser/Parser.py
BACAP_Parser/Rewards.py
BACAP_Parser/TabNameMapper.py
BACAP_Parser/__init__.py
BACAP_Parser/components_decoder.py
BACAP_Parser/constants.py
BACAP_Parser/nbt_decoder.py
BACAP_Parser/patterns.py
BACAP_Parser/utils.py
bacap_parser-0.5.7.dist-info/licenses/LICENSE
bacap_parser-0.5.7.dist-info/METADATA
bacap_parser-0.5.7.dist-info/WHEEL
bacap_parser-0.5.7.dist-info/top_level.txt
bacap_parser-0.5.7.dist-info/RECORD
