Metadata-Version: 2.4
Name: BACAP_Parser
Version: 0.5.7
Summary: Library to parse BlazeAndCavesAdvancementsPack and Addons for it
Author: ItzSkyReed, _Fedor_F
License: Creative Commons Attribution 4.0 International
Project-URL: Homepage, https://github.com/ItzSkyReed/BACAP_Parser
Classifier: Development Status :: 4 - Beta
Classifier: Programming Language :: Python :: 3.12
Classifier: Programming Language :: Python :: 3.13
Classifier: Operating System :: OS Independent
Requires-Python: >=3.12
License-File: LICENSE
Dynamic: license-file
